HEHEDB/HEHEDB.py
HEHEDB/__init__.py
HEHEDB-0.1.dist-info/METADATA
HEHEDB-0.1.dist-info/WHEEL
HEHEDB-0.1.dist-info/license.txt
HEHEDB-0.1.dist-info/top_level.txt
HEHEDB-0.1.dist-info/RECORD
