Metadata-Version: 2.1
Name: HEHEDB
Version: 0.1
Summary: a database query shorten
Author: PLC PEIRIS
Author-email: lashen985832@gmail.com
Classifier: Programming Language :: Python :: 3
Classifier: License :: OSI Approved :: MIT License
Classifier: Operating System :: OS Independent
License-File: license.txt
